pandalone/__init__.py
pandalone/_version.py
pandalone/components.py
pandalone/mappings.py
pandalone/pandata.py
pandalone/utils.py
pandalone/winutils.py
pandalone/xlsutils.py
pandalone/excel/ExcelPython.ico
pandalone/excel/pandalone.vba
pandalone/xleash/__init__.py
pandalone/xleash/_capture.py
pandalone/xleash/_filter.py
pandalone/xleash/_lasso.py
pandalone/xleash/_pandas_filters.py
pandalone/xleash/_parse.py
pandalone/xleash/io/__init__.py
pandalone/xleash/io/_xlrd.py
pandalone/xleash/io/backend.py
pandalone-0.5.0.dist-info/AUTHORS.rst
pandalone-0.5.0.dist-info/LICENSE.txt
pandalone-0.5.0.dist-info/METADATA
pandalone-0.5.0.dist-info/WHEEL
pandalone-0.5.0.dist-info/entry_points.txt
pandalone-0.5.0.dist-info/top_level.txt
pandalone-0.5.0.dist-info/zip-safe
pandalone-0.5.0.dist-info/RECORD
