Metadata-Version: 2.1
Name: pandalone
Version: 0.5.0
Summary: pandalone: process data-trees with relocatable-paths
Home-page: https://github.com/pandalone/pandalone
Author: Kostis Anagnostopoulos at European Commission (JRC)
Author-email: ankostis@gmail.com
License: UNKNOWN
Download-URL: https://github.com/pandalone/pandalone/tarball/v0.5.0
Project-URL: Documentation, https://pandalone.readthedocs.io/
Project-URL: Changes, https://github.com/pandalone/pandalone/blob/master/CHANGES.rst
Project-URL: Sources, https://github.com/pandalone/pandalone
Project-URL: Bug Tracker, https://github.com/pandalone/pandalone/issues
Keywords: python,utility,library,data,tree,processing,calculation,dependencies,resolution,scientific,engineering,pandas,simulink
Platform: any
Classifier: Programming Language :: Python
Classifier: Programming Language :: Python :: 3.6
Classifier: Programming Language :: Python :: 3.7
Classifier: Programming Language :: Python :: 3.8
Classifier: Programming Language :: Python :: Implementation :: CPython
Classifier: Development Status :: 4 - Beta
Classifier: Natural Language :: English
Classifier: Intended Audience :: Developers
Classifier: Intended Audience :: Science/Research
Classifier: Intended Audience :: Manufacturing
Classifier: Environment :: Console
Classifier: License :: OSI Approved :: European Union Public Licence 1.1 (EUPL 1.1)
Classifier: Operating System :: MacOS :: MacOS X
Classifier: Operating System :: Microsoft :: Windows
Classifier: Operating System :: POSIX
Classifier: Operating System :: Unix
Classifier: Operating System :: OS Independent
Classifier: Topic :: Scientific/Engineering
Classifier: Topic :: Scientific/Engineering :: Information Analysis
Classifier: Topic :: Software Development :: Libraries :: Python Modules
Classifier: Topic :: Utilities
Requires-Python: >=3.6
Requires-Dist: toolz
Requires-Dist: jsonschema (>=3.0.0)
Requires-Dist: numpy
Requires-Dist: asteval (>=0.9.7)
Provides-Extra: all
Requires-Dist: sphinx (>=1.3) ; extra == 'all'
Requires-Dist: pandas ; extra == 'all'
Requires-Dist: easygui (!=0.98) ; extra == 'all'
Requires-Dist: xlrd ; extra == 'all'
Requires-Dist: pytest ; extra == 'all'
Requires-Dist: pytest-cov ; extra == 'all'
Requires-Dist: pytest-sphinx ; extra == 'all'
Requires-Dist: docutils ; extra == 'all'
Requires-Dist: coveralls ; extra == 'all'
Requires-Dist: docopt ; extra == 'all'
Requires-Dist: ddt ; extra == 'all'
Requires-Dist: openpyxl ; extra == 'all'
Requires-Dist: wheel ; extra == 'all'
Requires-Dist: twine ; extra == 'all'
Requires-Dist: pylint ; extra == 'all'
Requires-Dist: black ; extra == 'all'
Requires-Dist: pre-commit ; extra == 'all'
Requires-Dist: doc8 ; extra == 'all'
Requires-Dist: sphinx-autobuild ; extra == 'all'
Requires-Dist: xlwings (>=0.9.2) ; (sys_platform == "win32") and extra == 'all'
Provides-Extra: dev
Requires-Dist: sphinx (>=1.3) ; extra == 'dev'
Requires-Dist: pandas ; extra == 'dev'
Requires-Dist: easygui (!=0.98) ; extra == 'dev'
Requires-Dist: xlrd ; extra == 'dev'
Requires-Dist: pytest ; extra == 'dev'
Requires-Dist: pytest-cov ; extra == 'dev'
Requires-Dist: pytest-sphinx ; extra == 'dev'
Requires-Dist: docutils ; extra == 'dev'
Requires-Dist: coveralls ; extra == 'dev'
Requires-Dist: docopt ; extra == 'dev'
Requires-Dist: ddt ; extra == 'dev'
Requires-Dist: openpyxl ; extra == 'dev'
Requires-Dist: wheel ; extra == 'dev'
Requires-Dist: twine ; extra == 'dev'
Requires-Dist: pylint ; extra == 'dev'
Requires-Dist: black ; extra == 'dev'
Requires-Dist: pre-commit ; extra == 'dev'
Requires-Dist: doc8 ; extra == 'dev'
Requires-Dist: sphinx-autobuild ; extra == 'dev'
Requires-Dist: xlwings (>=0.9.2) ; (sys_platform == "win32") and extra == 'dev'
Provides-Extra: doc
Requires-Dist: sphinx (>=1.3) ; extra == 'doc'
Provides-Extra: excel
Requires-Dist: easygui (!=0.98) ; extra == 'excel'
Requires-Dist: xlwings (>=0.9.2) ; (sys_platform == "win32") and extra == 'excel'
Provides-Extra: pandas
Requires-Dist: pandas ; extra == 'pandas'
Provides-Extra: test
Requires-Dist: sphinx (>=1.3) ; extra == 'test'
Requires-Dist: pandas ; extra == 'test'
Requires-Dist: easygui (!=0.98) ; extra == 'test'
Requires-Dist: xlrd ; extra == 'test'
Requires-Dist: pytest ; extra == 'test'
Requires-Dist: pytest-cov ; extra == 'test'
Requires-Dist: pytest-sphinx ; extra == 'test'
Requires-Dist: docutils ; extra == 'test'
Requires-Dist: coveralls ; extra == 'test'
Requires-Dist: docopt ; extra == 'test'
Requires-Dist: ddt ; extra == 'test'
Requires-Dist: openpyxl ; extra == 'test'
Requires-Dist: xlwings (>=0.9.2) ; (sys_platform == "win32") and extra == 'test'
Provides-Extra: xlrd
Requires-Dist: xlrd ; extra == 'xlrd'
